sendrella/.pytest_cache/.gitignore
sendrella/.pytest_cache/CACHEDIR.TAG
sendrella/.pytest_cache/README.md
sendrella/.pytest_cache/v/cache/lastfailed
sendrella/.pytest_cache/v/cache/nodeids
sendrella/.pytest_cache/v/cache/stepwise
sendrella/__init__.py
sendrella/client.py
sendrella/config.py
sendrella/endpoints/__init__.py
sendrella/endpoints/bounce.py
sendrella/endpoints/temp_mail.py
sendrella/endpoints/utils.py
sendrella/examples/.keep
sendrella/examples/bounce_logs.py
sendrella/examples/check_bounce.py
sendrella/examples/check_disposable.py
sendrella/examples/get_credits.py
sendrella/examples/temp_logs.py
sendrella/examples/validate_key.py
sendrella/exceptions.py
sendrella/http.py
sendrella/LICENSE
sendrella/models/__init__.py
sendrella/models/response.py
sendrella/pyproject.toml
sendrella/README.md
sendrella-0.1.1.dist-info/LICENSE
sendrella-0.1.1.dist-info/METADATA
sendrella-0.1.1.dist-info/WHEEL
sendrella-0.1.1.dist-info/RECORD
