Metadata-Version: 2.3
Name: sendrella
Version: 0.1.1
Summary: Official Python SDK for the Sendrella API – email validation, bounce checking, and disposable detection.
License: MIT
Keywords: email,validation,sdk,bounce,api,sendrella
Author: Salman Khan
Author-email: salman@sendrella.com
Requires-Python: >=3.7
Classifier: License :: OSI Approved :: MIT License
Classifier: Programming Language :: Python :: 3
Classifier: Programming Language :: Python :: 3.7
Classifier: Programming Language :: Python :: 3.8
Classifier: Programming Language :: Python :: 3.9
Classifier: Programming Language :: Python :: 3.10
Classifier: Programming Language :: Python :: 3.11
Classifier: Programming Language :: Python :: 3.12
Classifier: Programming Language :: Python :: 3.13
Requires-Dist: requests (>=2.31.0)
Project-URL: Documentation, https://swagger.sendrella.com
Project-URL: Homepage, https://sendrella.com
Project-URL: Repository, https://github.com/Salman0x01/sendrella-python-sdk
